p5magic/__init__.py
p5magic/p5magic.py
p5magic-2.5.0.dist-info/METADATA
p5magic-2.5.0.dist-info/WHEEL
p5magic-2.5.0.dist-info/top_level.txt
p5magic-2.5.0.dist-info/RECORD
